pywebwizard/__init__.py
pywebwizard/utils/__init__.py
pywebwizard/utils/ai_controller.py
pywebwizard/utils/config.py
pywebwizard/utils/data.py
pywebwizard/utils/exceptions.py
pywebwizard/utils/functions.py
pywebwizard/utils/hogwarts.py
pywebwizard/utils/logger.py
pywebwizard/utils/parsers.py
pywebwizard-1.3.35.dist-info/METADATA
pywebwizard-1.3.35.dist-info/WHEEL
pywebwizard-1.3.35.dist-info/top_level.txt
pywebwizard-1.3.35.dist-info/RECORD
