Metadata-Version: 2.4
Name: pywebwizard
Version: 1.3.35
Summary: Definitive Python 3 library for automatize Web Browser actions...
Home-page: https://gitlab.com/connorlilhomer/pywebwizard
Download-URL: https://gitlab.com/connorlilhomer/pywebwizard/-/archive/main/webwizard-1.3.35.tar.gz
Author: ConnorLilHomer
Author-email: info@parendum.com
Maintainer: ConnorLilHomer
Maintainer-email: info@parendum.com
License: MIT
Keywords: web,automation,browser,scraping,python,selenium,headless,browsing,task,data,extraction,multi-browser,support,workflow,UI,testing,YAML,configuration,cross-platform,form,filling,Selenium,integration,dynamic,web,interactions,automated,navigation,control,navegador,extracción,datos,pruebas,automatización,interacciones,sin,cabeza,automatización de navegadores,scrape,bot,robot,web scraping,crawler,form automation,dom manipulation,page load automation,multi-tab support,parallel tasks,captcha b
Platform: Windows
Platform: Linux
Platform: MacOS
Classifier: Programming Language :: Python :: 3
Classifier: Operating System :: OS Independent
Requires-Python: >=3.8
Requires-Dist: selenium
Requires-Dist: pyyaml
Requires-Dist: requests
Requires-Dist: setuptools
Requires-Dist: twine
Requires-Dist: pykeepass
Requires-Dist: undetected_chromedriver
Requires-Dist: pyotp
Requires-Dist: openai
Dynamic: author
Dynamic: author-email
Dynamic: classifier
Dynamic: download-url
Dynamic: home-page
Dynamic: keywords
Dynamic: license
Dynamic: maintainer
Dynamic: maintainer-email
Dynamic: platform
Dynamic: requires-dist
Dynamic: requires-python
Dynamic: summary
